[
	{
		"rank": 100,
		"data": [
			{
				"score": 7426.0,
				"summaryTime": "2019-02-19T15:30:00+09:00"
			},
			{
				"score": 14442.0,
				"summaryTime": "2019-02-19T16:00:00+09:00"
			},
			{
				"score": 21596.0,
				"summaryTime": "2019-02-19T16:30:00+09:00"
			},
			{
				"score": 28064.0,
				"summaryTime": "2019-02-19T17:00:00+09:00"
			},
			{
				"score": 33924.0,
				"summaryTime": "2019-02-19T17:30:00+09:00"
			},
			{
				"score": 38176.0,
				"summaryTime": "2019-02-19T18:00:00+09:00"
			},
			{
				"score": 43526.0,
				"summaryTime": "2019-02-19T18:30:00+09:00"
			},
			{
				"score": 49024.0,
				"summaryTime": "2019-02-19T19:00:00+09:00"
			},
			{
				"score": 52566.0,
				"summaryTime": "2019-02-19T19:30:00+09:00"
			},
			{
				"score": 55394.0,
				"summaryTime": "2019-02-19T20:00:00+09:00"
			},
			{
				"score": 59416.0,
				"summaryTime": "2019-02-19T20:30:00+09:00"
			},
			{
				"score": 64380.0,
				"summaryTime": "2019-02-19T21:00:00+09:00"
			},
			{
				"score": 69230.0,
				"summaryTime": "2019-02-19T21:30:00+09:00"
			},
			{
				"score": 74482.0,
				"summaryTime": "2019-02-19T22:00:00+09:00"
			},
			{
				"score": 78996.0,
				"summaryTime": "2019-02-19T22:30:00+09:00"
			},
			{
				"score": 84352.0,
				"summaryTime": "2019-02-19T23:00:00+09:00"
			},
			{
				"score": 89691.0,
				"summaryTime": "2019-02-19T23:30:00+09:00"
			},
			{
				"score": 93569.0,
				"summaryTime": "2019-02-20T00:00:00+09:00"
			},
			{
				"score": 95858.0,
				"summaryTime": "2019-02-20T00:30:00+09:00"
			},
			{
				"score": 98846.0,
				"summaryTime": "2019-02-20T01:00:00+09:00"
			},
			{
				"score": 102448.0,
				"summaryTime": "2019-02-20T01:30:00+09:00"
			},
			{
				"score": 105978.0,
				"summaryTime": "2019-02-20T02:00:00+09:00"
			},
			{
				"score": 108094.0,
				"summaryTime": "2019-02-20T02:30:00+09:00"
			},
			{
				"score": 110608.0,
				"summaryTime": "2019-02-20T03:00:00+09:00"
			},
			{
				"score": 111432.0,
				"summaryTime": "2019-02-20T03:30:00+09:00"
			},
			{
				"score": 113284.0,
				"summaryTime": "2019-02-20T04:00:00+09:00"
			},
			{
				"score": 115456.0,
				"summaryTime": "2019-02-20T04:30:00+09:00"
			},
			{
				"score": 117040.0,
				"summaryTime": "2019-02-20T05:00:00+09:00"
			},
			{
				"score": 119648.0,
				"summaryTime": "2019-02-20T05:30:00+09:00"
			},
			{
				"score": 120156.0,
				"summaryTime": "2019-02-20T06:00:00+09:00"
			},
			{
				"score": 120216.0,
				"summaryTime": "2019-02-20T06:30:00+09:00"
			},
			{
				"score": 121393.0,
				"summaryTime": "2019-02-20T07:00:00+09:00"
			},
			{
				"score": 122382.0,
				"summaryTime": "2019-02-20T07:30:00+09:00"
			},
			{
				"score": 124728.0,
				"summaryTime": "2019-02-20T08:00:00+09:00"
			},
			{
				"score": 129130.0,
				"summaryTime": "2019-02-20T08:30:00+09:00"
			},
			{
				"score": 131178.0,
				"summaryTime": "2019-02-20T09:00:00+09:00"
			},
			{
				"score": 133393.0,
				"summaryTime": "2019-02-20T09:30:00+09:00"
			},
			{
				"score": 134379.0,
				"summaryTime": "2019-02-20T10:00:00+09:00"
			},
			{
				"score": 135675.0,
				"summaryTime": "2019-02-20T10:30:00+09:00"
			},
			{
				"score": 137521.0,
				"summaryTime": "2019-02-20T11:00:00+09:00"
			},
			{
				"score": 138776.0,
				"summaryTime": "2019-02-20T11:30:00+09:00"
			},
			{
				"score": 141880.0,
				"summaryTime": "2019-02-20T12:00:00+09:00"
			},
			{
				"score": 147304.0,
				"summaryTime": "2019-02-20T12:30:00+09:00"
			},
			{
				"score": 150688.0,
				"summaryTime": "2019-02-20T13:00:00+09:00"
			},
			{
				"score": 152614.0,
				"summaryTime": "2019-02-20T13:30:00+09:00"
			},
			{
				"score": 158186.0,
				"summaryTime": "2019-02-20T14:00:00+09:00"
			},
			{
				"score": 161398.0,
				"summaryTime": "2019-02-20T14:30:00+09:00"
			},
			{
				"score": 161456.0,
				"summaryTime": "2019-02-20T15:00:00+09:00"
			},
			{
				"score": 163442.0,
				"summaryTime": "2019-02-20T15:30:00+09:00"
			},
			{
				"score": 164780.0,
				"summaryTime": "2019-02-20T16:00:00+09:00"
			},
			{
				"score": 165304.0,
				"summaryTime": "2019-02-20T16:30:00+09:00"
			},
			{
				"score": 168774.0,
				"summaryTime": "2019-02-20T17:00:00+09:00"
			},
			{
				"score": 172356.0,
				"summaryTime": "2019-02-20T17:30:00+09:00"
			},
			{
				"score": 177850.0,
				"summaryTime": "2019-02-20T18:00:00+09:00"
			},
			{
				"score": 182348.0,
				"summaryTime": "2019-02-20T18:30:00+09:00"
			},
			{
				"score": 186774.0,
				"summaryTime": "2019-02-20T19:00:00+09:00"
			},
			{
				"score": 191648.0,
				"summaryTime": "2019-02-20T19:30:00+09:00"
			},
			{
				"score": 195874.0,
				"summaryTime": "2019-02-20T20:00:00+09:00"
			},
			{
				"score": 200412.0,
				"summaryTime": "2019-02-20T20:30:00+09:00"
			},
			{
				"score": 202612.0,
				"summaryTime": "2019-02-20T21:00:00+09:00"
			},
			{
				"score": 203330.0,
				"summaryTime": "2019-02-20T21:30:00+09:00"
			},
			{
				"score": 210692.0,
				"summaryTime": "2019-02-20T22:00:00+09:00"
			},
			{
				"score": 214340.0,
				"summaryTime": "2019-02-20T22:30:00+09:00"
			},
			{
				"score": 221224.0,
				"summaryTime": "2019-02-20T23:00:00+09:00"
			},
			{
				"score": 224224.0,
				"summaryTime": "2019-02-20T23:30:00+09:00"
			},
			{
				"score": 226982.0,
				"summaryTime": "2019-02-21T00:00:00+09:00"
			},
			{
				"score": 230012.0,
				"summaryTime": "2019-02-21T00:30:00+09:00"
			},
			{
				"score": 234596.0,
				"summaryTime": "2019-02-21T01:00:00+09:00"
			},
			{
				"score": 238581.0,
				"summaryTime": "2019-02-21T01:30:00+09:00"
			},
			{
				"score": 240495.0,
				"summaryTime": "2019-02-21T02:00:00+09:00"
			},
			{
				"score": 244032.0,
				"summaryTime": "2019-02-21T02:30:00+09:00"
			},
			{
				"score": 245254.0,
				"summaryTime": "2019-02-21T03:00:00+09:00"
			},
			{
				"score": 249968.0,
				"summaryTime": "2019-02-21T03:30:00+09:00"
			},
			{
				"score": 251854.0,
				"summaryTime": "2019-02-21T04:00:00+09:00"
			},
			{
				"score": 251854.0,
				"summaryTime": "2019-02-21T04:30:00+09:00"
			},
			{
				"score": 251854.0,
				"summaryTime": "2019-02-21T05:00:00+09:00"
			},
			{
				"score": 254712.0,
				"summaryTime": "2019-02-21T05:30:00+09:00"
			},
			{
				"score": 254870.0,
				"summaryTime": "2019-02-21T06:00:00+09:00"
			},
			{
				"score": 255410.0,
				"summaryTime": "2019-02-21T06:30:00+09:00"
			},
			{
				"score": 259238.0,
				"summaryTime": "2019-02-21T07:00:00+09:00"
			},
			{
				"score": 260550.0,
				"summaryTime": "2019-02-21T07:30:00+09:00"
			},
			{
				"score": 260550.0,
				"summaryTime": "2019-02-21T08:00:00+09:00"
			},
			{
				"score": 265636.0,
				"summaryTime": "2019-02-21T08:30:00+09:00"
			},
			{
				"score": 266476.0,
				"summaryTime": "2019-02-21T09:00:00+09:00"
			},
			{
				"score": 270084.0,
				"summaryTime": "2019-02-21T09:30:00+09:00"
			},
			{
				"score": 270336.0,
				"summaryTime": "2019-02-21T10:00:00+09:00"
			},
			{
				"score": 275948.0,
				"summaryTime": "2019-02-21T10:30:00+09:00"
			},
			{
				"score": 276996.0,
				"summaryTime": "2019-02-21T11:00:00+09:00"
			},
			{
				"score": 278648.0,
				"summaryTime": "2019-02-21T11:30:00+09:00"
			},
			{
				"score": 279036.0,
				"summaryTime": "2019-02-21T12:00:00+09:00"
			},
			{
				"score": 282064.0,
				"summaryTime": "2019-02-21T12:30:00+09:00"
			},
			{
				"score": 286000.0,
				"summaryTime": "2019-02-21T13:00:00+09:00"
			},
			{
				"score": 288076.0,
				"summaryTime": "2019-02-21T13:30:00+09:00"
			},
			{
				"score": 290520.0,
				"summaryTime": "2019-02-21T14:00:00+09:00"
			},
			{
				"score": 291888.0,
				"summaryTime": "2019-02-21T14:30:00+09:00"
			},
			{
				"score": 293900.0,
				"summaryTime": "2019-02-21T15:00:00+09:00"
			},
			{
				"score": 296918.0,
				"summaryTime": "2019-02-21T15:30:00+09:00"
			},
			{
				"score": 297060.0,
				"summaryTime": "2019-02-21T16:00:00+09:00"
			},
			{
				"score": 298645.0,
				"summaryTime": "2019-02-21T16:30:00+09:00"
			},
			{
				"score": 301181.0,
				"summaryTime": "2019-02-21T17:00:00+09:00"
			},
			{
				"score": 303040.0,
				"summaryTime": "2019-02-21T17:30:00+09:00"
			},
			{
				"score": 303040.0,
				"summaryTime": "2019-02-21T18:00:00+09:00"
			},
			{
				"score": 306870.0,
				"summaryTime": "2019-02-21T18:30:00+09:00"
			},
			{
				"score": 308674.0,
				"summaryTime": "2019-02-21T19:00:00+09:00"
			},
			{
				"score": 311132.0,
				"summaryTime": "2019-02-21T19:30:00+09:00"
			},
			{
				"score": 314486.0,
				"summaryTime": "2019-02-21T20:00:00+09:00"
			},
			{
				"score": 318444.0,
				"summaryTime": "2019-02-21T20:30:00+09:00"
			},
			{
				"score": 319642.0,
				"summaryTime": "2019-02-21T21:00:00+09:00"
			},
			{
				"score": 324842.0,
				"summaryTime": "2019-02-21T21:30:00+09:00"
			},
			{
				"score": 330306.0,
				"summaryTime": "2019-02-21T22:00:00+09:00"
			},
			{
				"score": 335172.0,
				"summaryTime": "2019-02-21T22:30:00+09:00"
			},
			{
				"score": 338514.0,
				"summaryTime": "2019-02-21T23:00:00+09:00"
			},
			{
				"score": 345932.0,
				"summaryTime": "2019-02-21T23:30:00+09:00"
			},
			{
				"score": 353296.0,
				"summaryTime": "2019-02-22T00:00:00+09:00"
			},
			{
				"score": 359252.0,
				"summaryTime": "2019-02-22T00:30:00+09:00"
			},
			{
				"score": 364448.0,
				"summaryTime": "2019-02-22T01:00:00+09:00"
			},
			{
				"score": 369962.0,
				"summaryTime": "2019-02-22T01:30:00+09:00"
			},
			{
				"score": 371402.0,
				"summaryTime": "2019-02-22T02:00:00+09:00"
			},
			{
				"score": 371402.0,
				"summaryTime": "2019-02-22T02:30:00+09:00"
			},
			{
				"score": 371402.0,
				"summaryTime": "2019-02-22T03:00:00+09:00"
			},
			{
				"score": 376472.0,
				"summaryTime": "2019-02-22T03:30:00+09:00"
			},
			{
				"score": 377654.0,
				"summaryTime": "2019-02-22T04:00:00+09:00"
			},
			{
				"score": 381317.0,
				"summaryTime": "2019-02-22T04:30:00+09:00"
			},
			{
				"score": 384896.0,
				"summaryTime": "2019-02-22T05:00:00+09:00"
			},
			{
				"score": 384896.0,
				"summaryTime": "2019-02-22T05:30:00+09:00"
			},
			{
				"score": 384896.0,
				"summaryTime": "2019-02-22T06:00:00+09:00"
			},
			{
				"score": 388476.0,
				"summaryTime": "2019-02-22T06:30:00+09:00"
			},
			{
				"score": 391780.0,
				"summaryTime": "2019-02-22T07:00:00+09:00"
			},
			{
				"score": 391780.0,
				"summaryTime": "2019-02-22T07:30:00+09:00"
			},
			{
				"score": 391780.0,
				"summaryTime": "2019-02-22T08:00:00+09:00"
			},
			{
				"score": 391780.0,
				"summaryTime": "2019-02-22T08:30:00+09:00"
			},
			{
				"score": 391780.0,
				"summaryTime": "2019-02-22T09:00:00+09:00"
			},
			{
				"score": 391780.0,
				"summaryTime": "2019-02-22T09:30:00+09:00"
			},
			{
				"score": 399840.0,
				"summaryTime": "2019-02-22T10:00:00+09:00"
			},
			{
				"score": 405977.0,
				"summaryTime": "2019-02-22T10:30:00+09:00"
			},
			{
				"score": 405977.0,
				"summaryTime": "2019-02-22T11:00:00+09:00"
			},
			{
				"score": 406432.0,
				"summaryTime": "2019-02-22T11:30:00+09:00"
			},
			{
				"score": 410280.0,
				"summaryTime": "2019-02-22T12:00:00+09:00"
			},
			{
				"score": 412780.0,
				"summaryTime": "2019-02-22T12:30:00+09:00"
			},
			{
				"score": 417908.0,
				"summaryTime": "2019-02-22T13:00:00+09:00"
			},
			{
				"score": 420608.0,
				"summaryTime": "2019-02-22T13:30:00+09:00"
			},
			{
				"score": 421374.0,
				"summaryTime": "2019-02-22T14:00:00+09:00"
			},
			{
				"score": 430038.0,
				"summaryTime": "2019-02-22T14:30:00+09:00"
			},
			{
				"score": 432650.0,
				"summaryTime": "2019-02-22T15:00:00+09:00"
			},
			{
				"score": 433342.0,
				"summaryTime": "2019-02-22T15:30:00+09:00"
			},
			{
				"score": 434252.0,
				"summaryTime": "2019-02-22T16:00:00+09:00"
			},
			{
				"score": 434252.0,
				"summaryTime": "2019-02-22T16:30:00+09:00"
			},
			{
				"score": 435454.0,
				"summaryTime": "2019-02-22T17:00:00+09:00"
			},
			{
				"score": 437470.0,
				"summaryTime": "2019-02-22T17:30:00+09:00"
			},
			{
				"score": 441968.0,
				"summaryTime": "2019-02-22T18:00:00+09:00"
			},
			{
				"score": 445666.0,
				"summaryTime": "2019-02-22T18:30:00+09:00"
			},
			{
				"score": 445666.0,
				"summaryTime": "2019-02-22T19:00:00+09:00"
			},
			{
				"score": 445666.0,
				"summaryTime": "2019-02-22T19:30:00+09:00"
			},
			{
				"score": 448180.0,
				"summaryTime": "2019-02-22T20:00:00+09:00"
			},
			{
				"score": 452019.0,
				"summaryTime": "2019-02-22T20:30:00+09:00"
			},
			{
				"score": 453957.0,
				"summaryTime": "2019-02-22T21:00:00+09:00"
			},
			{
				"score": 461137.0,
				"summaryTime": "2019-02-22T21:30:00+09:00"
			},
			{
				"score": 463538.0,
				"summaryTime": "2019-02-22T22:00:00+09:00"
			},
			{
				"score": 472556.0,
				"summaryTime": "2019-02-22T22:30:00+09:00"
			},
			{
				"score": 478520.0,
				"summaryTime": "2019-02-22T23:00:00+09:00"
			}
		]
	},
	{
		"rank": 2500,
		"data": [
			{
				"score": 1376.0,
				"summaryTime": "2019-02-19T15:30:00+09:00"
			},
			{
				"score": 2420.0,
				"summaryTime": "2019-02-19T16:00:00+09:00"
			},
			{
				"score": 3112.0,
				"summaryTime": "2019-02-19T16:30:00+09:00"
			},
			{
				"score": 3628.0,
				"summaryTime": "2019-02-19T17:00:00+09:00"
			},
			{
				"score": 4132.0,
				"summaryTime": "2019-02-19T17:30:00+09:00"
			},
			{
				"score": 4560.0,
				"summaryTime": "2019-02-19T18:00:00+09:00"
			},
			{
				"score": 5046.0,
				"summaryTime": "2019-02-19T18:30:00+09:00"
			},
			{
				"score": 5509.0,
				"summaryTime": "2019-02-19T19:00:00+09:00"
			},
			{
				"score": 5956.0,
				"summaryTime": "2019-02-19T19:30:00+09:00"
			},
			{
				"score": 6652.0,
				"summaryTime": "2019-02-19T20:00:00+09:00"
			},
			{
				"score": 7188.0,
				"summaryTime": "2019-02-19T20:30:00+09:00"
			},
			{
				"score": 7712.0,
				"summaryTime": "2019-02-19T21:00:00+09:00"
			},
			{
				"score": 8380.0,
				"summaryTime": "2019-02-19T21:30:00+09:00"
			},
			{
				"score": 9232.0,
				"summaryTime": "2019-02-19T22:00:00+09:00"
			},
			{
				"score": 10040.0,
				"summaryTime": "2019-02-19T22:30:00+09:00"
			},
			{
				"score": 10568.0,
				"summaryTime": "2019-02-19T23:00:00+09:00"
			},
			{
				"score": 10914.0,
				"summaryTime": "2019-02-19T23:30:00+09:00"
			},
			{
				"score": 11222.0,
				"summaryTime": "2019-02-20T00:00:00+09:00"
			},
			{
				"score": 11544.0,
				"summaryTime": "2019-02-20T00:30:00+09:00"
			},
			{
				"score": 12048.0,
				"summaryTime": "2019-02-20T01:00:00+09:00"
			},
			{
				"score": 12412.0,
				"summaryTime": "2019-02-20T01:30:00+09:00"
			},
			{
				"score": 12634.0,
				"summaryTime": "2019-02-20T02:00:00+09:00"
			},
			{
				"score": 12842.0,
				"summaryTime": "2019-02-20T02:30:00+09:00"
			},
			{
				"score": 13018.0,
				"summaryTime": "2019-02-20T03:00:00+09:00"
			},
			{
				"score": 13189.0,
				"summaryTime": "2019-02-20T03:30:00+09:00"
			},
			{
				"score": 13332.0,
				"summaryTime": "2019-02-20T04:00:00+09:00"
			},
			{
				"score": 13428.0,
				"summaryTime": "2019-02-20T04:30:00+09:00"
			},
			{
				"score": 13520.0,
				"summaryTime": "2019-02-20T05:00:00+09:00"
			},
			{
				"score": 13584.0,
				"summaryTime": "2019-02-20T05:30:00+09:00"
			},
			{
				"score": 13743.0,
				"summaryTime": "2019-02-20T06:00:00+09:00"
			},
			{
				"score": 13912.0,
				"summaryTime": "2019-02-20T06:30:00+09:00"
			},
			{
				"score": 14028.0,
				"summaryTime": "2019-02-20T07:00:00+09:00"
			},
			{
				"score": 14234.0,
				"summaryTime": "2019-02-20T07:30:00+09:00"
			},
			{
				"score": 14396.0,
				"summaryTime": "2019-02-20T08:00:00+09:00"
			},
			{
				"score": 14546.0,
				"summaryTime": "2019-02-20T08:30:00+09:00"
			},
			{
				"score": 14778.0,
				"summaryTime": "2019-02-20T09:00:00+09:00"
			},
			{
				"score": 15018.0,
				"summaryTime": "2019-02-20T09:30:00+09:00"
			},
			{
				"score": 15239.0,
				"summaryTime": "2019-02-20T10:00:00+09:00"
			},
			{
				"score": 15472.0,
				"summaryTime": "2019-02-20T10:30:00+09:00"
			},
			{
				"score": 15738.0,
				"summaryTime": "2019-02-20T11:00:00+09:00"
			},
			{
				"score": 15952.0,
				"summaryTime": "2019-02-20T11:30:00+09:00"
			},
			{
				"score": 16142.0,
				"summaryTime": "2019-02-20T12:00:00+09:00"
			},
			{
				"score": 16376.0,
				"summaryTime": "2019-02-20T12:30:00+09:00"
			},
			{
				"score": 16660.0,
				"summaryTime": "2019-02-20T13:00:00+09:00"
			},
			{
				"score": 16940.0,
				"summaryTime": "2019-02-20T13:30:00+09:00"
			},
			{
				"score": 17288.0,
				"summaryTime": "2019-02-20T14:00:00+09:00"
			},
			{
				"score": 17552.0,
				"summaryTime": "2019-02-20T14:30:00+09:00"
			},
			{
				"score": 17842.0,
				"summaryTime": "2019-02-20T15:00:00+09:00"
			},
			{
				"score": 18024.0,
				"summaryTime": "2019-02-20T15:30:00+09:00"
			},
			{
				"score": 18240.0,
				"summaryTime": "2019-02-20T16:00:00+09:00"
			},
			{
				"score": 18448.0,
				"summaryTime": "2019-02-20T16:30:00+09:00"
			},
			{
				"score": 18774.0,
				"summaryTime": "2019-02-20T17:00:00+09:00"
			},
			{
				"score": 19056.0,
				"summaryTime": "2019-02-20T17:30:00+09:00"
			},
			{
				"score": 19484.0,
				"summaryTime": "2019-02-20T18:00:00+09:00"
			},
			{
				"score": 19740.0,
				"summaryTime": "2019-02-20T18:30:00+09:00"
			},
			{
				"score": 20080.0,
				"summaryTime": "2019-02-20T19:00:00+09:00"
			},
			{
				"score": 20360.0,
				"summaryTime": "2019-02-20T19:30:00+09:00"
			},
			{
				"score": 20737.0,
				"summaryTime": "2019-02-20T20:00:00+09:00"
			},
			{
				"score": 21220.0,
				"summaryTime": "2019-02-20T20:30:00+09:00"
			},
			{
				"score": 21682.0,
				"summaryTime": "2019-02-20T21:00:00+09:00"
			},
			{
				"score": 22385.0,
				"summaryTime": "2019-02-20T21:30:00+09:00"
			},
			{
				"score": 22978.0,
				"summaryTime": "2019-02-20T22:00:00+09:00"
			},
			{
				"score": 23500.0,
				"summaryTime": "2019-02-20T22:30:00+09:00"
			},
			{
				"score": 24244.0,
				"summaryTime": "2019-02-20T23:00:00+09:00"
			},
			{
				"score": 24988.0,
				"summaryTime": "2019-02-20T23:30:00+09:00"
			},
			{
				"score": 25324.0,
				"summaryTime": "2019-02-21T00:00:00+09:00"
			},
			{
				"score": 25780.0,
				"summaryTime": "2019-02-21T00:30:00+09:00"
			},
			{
				"score": 26380.0,
				"summaryTime": "2019-02-21T01:00:00+09:00"
			},
			{
				"score": 26740.0,
				"summaryTime": "2019-02-21T01:30:00+09:00"
			},
			{
				"score": 26943.0,
				"summaryTime": "2019-02-21T02:00:00+09:00"
			},
			{
				"score": 27168.0,
				"summaryTime": "2019-02-21T02:30:00+09:00"
			},
			{
				"score": 27438.0,
				"summaryTime": "2019-02-21T03:00:00+09:00"
			},
			{
				"score": 27697.0,
				"summaryTime": "2019-02-21T03:30:00+09:00"
			},
			{
				"score": 27920.0,
				"summaryTime": "2019-02-21T04:00:00+09:00"
			},
			{
				"score": 28173.0,
				"summaryTime": "2019-02-21T04:30:00+09:00"
			},
			{
				"score": 28260.0,
				"summaryTime": "2019-02-21T05:00:00+09:00"
			},
			{
				"score": 28338.0,
				"summaryTime": "2019-02-21T05:30:00+09:00"
			},
			{
				"score": 28402.0,
				"summaryTime": "2019-02-21T06:00:00+09:00"
			},
			{
				"score": 28528.0,
				"summaryTime": "2019-02-21T06:30:00+09:00"
			},
			{
				"score": 28730.0,
				"summaryTime": "2019-02-21T07:00:00+09:00"
			},
			{
				"score": 29040.0,
				"summaryTime": "2019-02-21T07:30:00+09:00"
			},
			{
				"score": 29368.0,
				"summaryTime": "2019-02-21T08:00:00+09:00"
			},
			{
				"score": 29858.0,
				"summaryTime": "2019-02-21T08:30:00+09:00"
			},
			{
				"score": 30026.0,
				"summaryTime": "2019-02-21T09:00:00+09:00"
			},
			{
				"score": 30143.0,
				"summaryTime": "2019-02-21T09:30:00+09:00"
			},
			{
				"score": 30356.0,
				"summaryTime": "2019-02-21T10:00:00+09:00"
			},
			{
				"score": 30524.0,
				"summaryTime": "2019-02-21T10:30:00+09:00"
			},
			{
				"score": 30644.0,
				"summaryTime": "2019-02-21T11:00:00+09:00"
			},
			{
				"score": 30760.0,
				"summaryTime": "2019-02-21T11:30:00+09:00"
			},
			{
				"score": 30865.0,
				"summaryTime": "2019-02-21T12:00:00+09:00"
			},
			{
				"score": 31060.0,
				"summaryTime": "2019-02-21T12:30:00+09:00"
			},
			{
				"score": 31322.0,
				"summaryTime": "2019-02-21T13:00:00+09:00"
			},
			{
				"score": 31621.0,
				"summaryTime": "2019-02-21T13:30:00+09:00"
			},
			{
				"score": 32000.0,
				"summaryTime": "2019-02-21T14:00:00+09:00"
			},
			{
				"score": 32068.0,
				"summaryTime": "2019-02-21T14:30:00+09:00"
			},
			{
				"score": 32308.0,
				"summaryTime": "2019-02-21T15:00:00+09:00"
			},
			{
				"score": 32378.0,
				"summaryTime": "2019-02-21T15:30:00+09:00"
			},
			{
				"score": 32500.0,
				"summaryTime": "2019-02-21T16:00:00+09:00"
			},
			{
				"score": 32648.0,
				"summaryTime": "2019-02-21T16:30:00+09:00"
			},
			{
				"score": 32796.0,
				"summaryTime": "2019-02-21T17:00:00+09:00"
			},
			{
				"score": 32928.0,
				"summaryTime": "2019-02-21T17:30:00+09:00"
			},
			{
				"score": 33040.0,
				"summaryTime": "2019-02-21T18:00:00+09:00"
			},
			{
				"score": 33230.0,
				"summaryTime": "2019-02-21T18:30:00+09:00"
			},
			{
				"score": 33558.0,
				"summaryTime": "2019-02-21T19:00:00+09:00"
			},
			{
				"score": 33933.0,
				"summaryTime": "2019-02-21T19:30:00+09:00"
			},
			{
				"score": 34372.0,
				"summaryTime": "2019-02-21T20:00:00+09:00"
			},
			{
				"score": 34716.0,
				"summaryTime": "2019-02-21T20:30:00+09:00"
			},
			{
				"score": 35180.0,
				"summaryTime": "2019-02-21T21:00:00+09:00"
			},
			{
				"score": 35638.0,
				"summaryTime": "2019-02-21T21:30:00+09:00"
			},
			{
				"score": 35946.0,
				"summaryTime": "2019-02-21T22:00:00+09:00"
			},
			{
				"score": 36674.0,
				"summaryTime": "2019-02-21T22:30:00+09:00"
			},
			{
				"score": 37215.0,
				"summaryTime": "2019-02-21T23:00:00+09:00"
			},
			{
				"score": 37778.0,
				"summaryTime": "2019-02-21T23:30:00+09:00"
			},
			{
				"score": 38180.0,
				"summaryTime": "2019-02-22T00:00:00+09:00"
			},
			{
				"score": 38520.0,
				"summaryTime": "2019-02-22T00:30:00+09:00"
			},
			{
				"score": 39160.0,
				"summaryTime": "2019-02-22T01:00:00+09:00"
			},
			{
				"score": 39280.0,
				"summaryTime": "2019-02-22T01:30:00+09:00"
			},
			{
				"score": 39460.0,
				"summaryTime": "2019-02-22T02:00:00+09:00"
			},
			{
				"score": 39698.0,
				"summaryTime": "2019-02-22T02:30:00+09:00"
			},
			{
				"score": 39794.0,
				"summaryTime": "2019-02-22T03:00:00+09:00"
			},
			{
				"score": 40090.0,
				"summaryTime": "2019-02-22T03:30:00+09:00"
			},
			{
				"score": 40180.0,
				"summaryTime": "2019-02-22T04:00:00+09:00"
			},
			{
				"score": 40254.0,
				"summaryTime": "2019-02-22T04:30:00+09:00"
			},
			{
				"score": 40300.0,
				"summaryTime": "2019-02-22T05:00:00+09:00"
			},
			{
				"score": 40364.0,
				"summaryTime": "2019-02-22T05:30:00+09:00"
			},
			{
				"score": 40487.0,
				"summaryTime": "2019-02-22T06:00:00+09:00"
			},
			{
				"score": 40766.0,
				"summaryTime": "2019-02-22T06:30:00+09:00"
			},
			{
				"score": 41016.0,
				"summaryTime": "2019-02-22T07:00:00+09:00"
			},
			{
				"score": 41148.0,
				"summaryTime": "2019-02-22T07:30:00+09:00"
			},
			{
				"score": 41264.0,
				"summaryTime": "2019-02-22T08:00:00+09:00"
			},
			{
				"score": 41380.0,
				"summaryTime": "2019-02-22T08:30:00+09:00"
			},
			{
				"score": 41653.0,
				"summaryTime": "2019-02-22T09:00:00+09:00"
			},
			{
				"score": 41802.0,
				"summaryTime": "2019-02-22T09:30:00+09:00"
			},
			{
				"score": 42024.0,
				"summaryTime": "2019-02-22T10:00:00+09:00"
			},
			{
				"score": 42144.0,
				"summaryTime": "2019-02-22T10:30:00+09:00"
			},
			{
				"score": 42266.0,
				"summaryTime": "2019-02-22T11:00:00+09:00"
			},
			{
				"score": 42450.0,
				"summaryTime": "2019-02-22T11:30:00+09:00"
			},
			{
				"score": 42664.0,
				"summaryTime": "2019-02-22T12:00:00+09:00"
			},
			{
				"score": 42960.0,
				"summaryTime": "2019-02-22T12:30:00+09:00"
			},
			{
				"score": 43268.0,
				"summaryTime": "2019-02-22T13:00:00+09:00"
			},
			{
				"score": 43577.0,
				"summaryTime": "2019-02-22T13:30:00+09:00"
			},
			{
				"score": 43711.0,
				"summaryTime": "2019-02-22T14:00:00+09:00"
			},
			{
				"score": 43880.0,
				"summaryTime": "2019-02-22T14:30:00+09:00"
			},
			{
				"score": 44220.0,
				"summaryTime": "2019-02-22T15:00:00+09:00"
			},
			{
				"score": 44460.0,
				"summaryTime": "2019-02-22T15:30:00+09:00"
			},
			{
				"score": 44778.0,
				"summaryTime": "2019-02-22T16:00:00+09:00"
			},
			{
				"score": 44980.0,
				"summaryTime": "2019-02-22T16:30:00+09:00"
			},
			{
				"score": 45148.0,
				"summaryTime": "2019-02-22T17:00:00+09:00"
			},
			{
				"score": 45402.0,
				"summaryTime": "2019-02-22T17:30:00+09:00"
			},
			{
				"score": 45766.0,
				"summaryTime": "2019-02-22T18:00:00+09:00"
			},
			{
				"score": 46061.0,
				"summaryTime": "2019-02-22T18:30:00+09:00"
			},
			{
				"score": 46300.0,
				"summaryTime": "2019-02-22T19:00:00+09:00"
			},
			{
				"score": 46627.0,
				"summaryTime": "2019-02-22T19:30:00+09:00"
			},
			{
				"score": 47020.0,
				"summaryTime": "2019-02-22T20:00:00+09:00"
			},
			{
				"score": 47434.0,
				"summaryTime": "2019-02-22T20:30:00+09:00"
			},
			{
				"score": 47940.0,
				"summaryTime": "2019-02-22T21:00:00+09:00"
			},
			{
				"score": 48386.0,
				"summaryTime": "2019-02-22T21:30:00+09:00"
			},
			{
				"score": 48808.0,
				"summaryTime": "2019-02-22T22:00:00+09:00"
			},
			{
				"score": 49422.0,
				"summaryTime": "2019-02-22T22:30:00+09:00"
			},
			{
				"score": 50128.0,
				"summaryTime": "2019-02-22T23:00:00+09:00"
			}
		]
	},
	{
		"rank": 5000,
		"data": [
			{
				"score": 860.0,
				"summaryTime": "2019-02-19T15:30:00+09:00"
			},
			{
				"score": 1758.0,
				"summaryTime": "2019-02-19T16:00:00+09:00"
			},
			{
				"score": 2068.0,
				"summaryTime": "2019-02-19T16:30:00+09:00"
			},
			{
				"score": 2372.0,
				"summaryTime": "2019-02-19T17:00:00+09:00"
			},
			{
				"score": 2560.0,
				"summaryTime": "2019-02-19T17:30:00+09:00"
			},
			{
				"score": 2700.0,
				"summaryTime": "2019-02-19T18:00:00+09:00"
			},
			{
				"score": 2980.0,
				"summaryTime": "2019-02-19T18:30:00+09:00"
			},
			{
				"score": 3256.0,
				"summaryTime": "2019-02-19T19:00:00+09:00"
			},
			{
				"score": 3480.0,
				"summaryTime": "2019-02-19T19:30:00+09:00"
			},
			{
				"score": 3746.0,
				"summaryTime": "2019-02-19T20:00:00+09:00"
			},
			{
				"score": 4120.0,
				"summaryTime": "2019-02-19T20:30:00+09:00"
			},
			{
				"score": 4488.0,
				"summaryTime": "2019-02-19T21:00:00+09:00"
			},
			{
				"score": 4840.0,
				"summaryTime": "2019-02-19T21:30:00+09:00"
			},
			{
				"score": 5246.0,
				"summaryTime": "2019-02-19T22:00:00+09:00"
			},
			{
				"score": 5540.0,
				"summaryTime": "2019-02-19T22:30:00+09:00"
			},
			{
				"score": 5854.0,
				"summaryTime": "2019-02-19T23:00:00+09:00"
			},
			{
				"score": 6238.0,
				"summaryTime": "2019-02-19T23:30:00+09:00"
			},
			{
				"score": 6540.0,
				"summaryTime": "2019-02-20T00:00:00+09:00"
			},
			{
				"score": 6806.0,
				"summaryTime": "2019-02-20T00:30:00+09:00"
			},
			{
				"score": 7090.0,
				"summaryTime": "2019-02-20T01:00:00+09:00"
			},
			{
				"score": 7244.0,
				"summaryTime": "2019-02-20T01:30:00+09:00"
			},
			{
				"score": 7396.0,
				"summaryTime": "2019-02-20T02:00:00+09:00"
			},
			{
				"score": 7532.0,
				"summaryTime": "2019-02-20T02:30:00+09:00"
			},
			{
				"score": 7634.0,
				"summaryTime": "2019-02-20T03:00:00+09:00"
			},
			{
				"score": 7736.0,
				"summaryTime": "2019-02-20T03:30:00+09:00"
			},
			{
				"score": 7820.0,
				"summaryTime": "2019-02-20T04:00:00+09:00"
			},
			{
				"score": 7896.0,
				"summaryTime": "2019-02-20T04:30:00+09:00"
			},
			{
				"score": 7954.0,
				"summaryTime": "2019-02-20T05:00:00+09:00"
			},
			{
				"score": 8012.0,
				"summaryTime": "2019-02-20T05:30:00+09:00"
			},
			{
				"score": 8094.0,
				"summaryTime": "2019-02-20T06:00:00+09:00"
			},
			{
				"score": 8192.0,
				"summaryTime": "2019-02-20T06:30:00+09:00"
			},
			{
				"score": 8326.0,
				"summaryTime": "2019-02-20T07:00:00+09:00"
			},
			{
				"score": 8490.0,
				"summaryTime": "2019-02-20T07:30:00+09:00"
			},
			{
				"score": 8662.0,
				"summaryTime": "2019-02-20T08:00:00+09:00"
			},
			{
				"score": 8804.0,
				"summaryTime": "2019-02-20T08:30:00+09:00"
			},
			{
				"score": 8950.0,
				"summaryTime": "2019-02-20T09:00:00+09:00"
			},
			{
				"score": 9048.0,
				"summaryTime": "2019-02-20T09:30:00+09:00"
			},
			{
				"score": 9146.0,
				"summaryTime": "2019-02-20T10:00:00+09:00"
			},
			{
				"score": 9228.0,
				"summaryTime": "2019-02-20T10:30:00+09:00"
			},
			{
				"score": 9370.0,
				"summaryTime": "2019-02-20T11:00:00+09:00"
			},
			{
				"score": 9520.0,
				"summaryTime": "2019-02-20T11:30:00+09:00"
			},
			{
				"score": 9680.0,
				"summaryTime": "2019-02-20T12:00:00+09:00"
			},
			{
				"score": 9840.0,
				"summaryTime": "2019-02-20T12:30:00+09:00"
			},
			{
				"score": 10068.0,
				"summaryTime": "2019-02-20T13:00:00+09:00"
			},
			{
				"score": 10172.0,
				"summaryTime": "2019-02-20T13:30:00+09:00"
			},
			{
				"score": 10304.0,
				"summaryTime": "2019-02-20T14:00:00+09:00"
			},
			{
				"score": 10444.0,
				"summaryTime": "2019-02-20T14:30:00+09:00"
			},
			{
				"score": 10588.0,
				"summaryTime": "2019-02-20T15:00:00+09:00"
			},
			{
				"score": 10710.0,
				"summaryTime": "2019-02-20T15:30:00+09:00"
			},
			{
				"score": 10820.0,
				"summaryTime": "2019-02-20T16:00:00+09:00"
			},
			{
				"score": 10940.0,
				"summaryTime": "2019-02-20T16:30:00+09:00"
			},
			{
				"score": 11075.0,
				"summaryTime": "2019-02-20T17:00:00+09:00"
			},
			{
				"score": 11187.0,
				"summaryTime": "2019-02-20T17:30:00+09:00"
			},
			{
				"score": 11344.0,
				"summaryTime": "2019-02-20T18:00:00+09:00"
			},
			{
				"score": 11476.0,
				"summaryTime": "2019-02-20T18:30:00+09:00"
			},
			{
				"score": 11640.0,
				"summaryTime": "2019-02-20T19:00:00+09:00"
			},
			{
				"score": 11840.0,
				"summaryTime": "2019-02-20T19:30:00+09:00"
			},
			{
				"score": 12085.0,
				"summaryTime": "2019-02-20T20:00:00+09:00"
			},
			{
				"score": 12348.0,
				"summaryTime": "2019-02-20T20:30:00+09:00"
			},
			{
				"score": 12566.0,
				"summaryTime": "2019-02-20T21:00:00+09:00"
			},
			{
				"score": 12762.0,
				"summaryTime": "2019-02-20T21:30:00+09:00"
			},
			{
				"score": 13072.0,
				"summaryTime": "2019-02-20T22:00:00+09:00"
			},
			{
				"score": 13352.0,
				"summaryTime": "2019-02-20T22:30:00+09:00"
			},
			{
				"score": 13584.0,
				"summaryTime": "2019-02-20T23:00:00+09:00"
			},
			{
				"score": 13796.0,
				"summaryTime": "2019-02-20T23:30:00+09:00"
			},
			{
				"score": 14036.0,
				"summaryTime": "2019-02-21T00:00:00+09:00"
			},
			{
				"score": 14264.0,
				"summaryTime": "2019-02-21T00:30:00+09:00"
			},
			{
				"score": 14484.0,
				"summaryTime": "2019-02-21T01:00:00+09:00"
			},
			{
				"score": 14660.0,
				"summaryTime": "2019-02-21T01:30:00+09:00"
			},
			{
				"score": 14768.0,
				"summaryTime": "2019-02-21T02:00:00+09:00"
			},
			{
				"score": 14906.0,
				"summaryTime": "2019-02-21T02:30:00+09:00"
			},
			{
				"score": 14960.0,
				"summaryTime": "2019-02-21T03:00:00+09:00"
			},
			{
				"score": 15040.0,
				"summaryTime": "2019-02-21T03:30:00+09:00"
			},
			{
				"score": 15084.0,
				"summaryTime": "2019-02-21T04:00:00+09:00"
			},
			{
				"score": 15160.0,
				"summaryTime": "2019-02-21T04:30:00+09:00"
			},
			{
				"score": 15218.0,
				"summaryTime": "2019-02-21T05:00:00+09:00"
			},
			{
				"score": 15280.0,
				"summaryTime": "2019-02-21T05:30:00+09:00"
			},
			{
				"score": 15350.0,
				"summaryTime": "2019-02-21T06:00:00+09:00"
			},
			{
				"score": 15448.0,
				"summaryTime": "2019-02-21T06:30:00+09:00"
			},
			{
				"score": 15602.0,
				"summaryTime": "2019-02-21T07:00:00+09:00"
			},
			{
				"score": 15760.0,
				"summaryTime": "2019-02-21T07:30:00+09:00"
			},
			{
				"score": 15864.0,
				"summaryTime": "2019-02-21T08:00:00+09:00"
			},
			{
				"score": 15980.0,
				"summaryTime": "2019-02-21T08:30:00+09:00"
			},
			{
				"score": 16080.0,
				"summaryTime": "2019-02-21T09:00:00+09:00"
			},
			{
				"score": 16156.0,
				"summaryTime": "2019-02-21T09:30:00+09:00"
			},
			{
				"score": 16240.0,
				"summaryTime": "2019-02-21T10:00:00+09:00"
			},
			{
				"score": 16344.0,
				"summaryTime": "2019-02-21T10:30:00+09:00"
			},
			{
				"score": 16458.0,
				"summaryTime": "2019-02-21T11:00:00+09:00"
			},
			{
				"score": 16584.0,
				"summaryTime": "2019-02-21T11:30:00+09:00"
			},
			{
				"score": 16680.0,
				"summaryTime": "2019-02-21T12:00:00+09:00"
			},
			{
				"score": 16884.0,
				"summaryTime": "2019-02-21T12:30:00+09:00"
			},
			{
				"score": 17041.0,
				"summaryTime": "2019-02-21T13:00:00+09:00"
			},
			{
				"score": 17180.0,
				"summaryTime": "2019-02-21T13:30:00+09:00"
			},
			{
				"score": 17316.0,
				"summaryTime": "2019-02-21T14:00:00+09:00"
			},
			{
				"score": 17456.0,
				"summaryTime": "2019-02-21T14:30:00+09:00"
			},
			{
				"score": 17580.0,
				"summaryTime": "2019-02-21T15:00:00+09:00"
			},
			{
				"score": 17662.0,
				"summaryTime": "2019-02-21T15:30:00+09:00"
			},
			{
				"score": 17780.0,
				"summaryTime": "2019-02-21T16:00:00+09:00"
			},
			{
				"score": 17928.0,
				"summaryTime": "2019-02-21T16:30:00+09:00"
			},
			{
				"score": 18026.0,
				"summaryTime": "2019-02-21T17:00:00+09:00"
			},
			{
				"score": 18174.0,
				"summaryTime": "2019-02-21T17:30:00+09:00"
			},
			{
				"score": 18273.0,
				"summaryTime": "2019-02-21T18:00:00+09:00"
			},
			{
				"score": 18381.0,
				"summaryTime": "2019-02-21T18:30:00+09:00"
			},
			{
				"score": 18536.0,
				"summaryTime": "2019-02-21T19:00:00+09:00"
			},
			{
				"score": 18703.0,
				"summaryTime": "2019-02-21T19:30:00+09:00"
			},
			{
				"score": 18973.0,
				"summaryTime": "2019-02-21T20:00:00+09:00"
			},
			{
				"score": 19230.0,
				"summaryTime": "2019-02-21T20:30:00+09:00"
			},
			{
				"score": 19446.0,
				"summaryTime": "2019-02-21T21:00:00+09:00"
			},
			{
				"score": 19628.0,
				"summaryTime": "2019-02-21T21:30:00+09:00"
			},
			{
				"score": 19880.0,
				"summaryTime": "2019-02-21T22:00:00+09:00"
			},
			{
				"score": 20065.0,
				"summaryTime": "2019-02-21T22:30:00+09:00"
			},
			{
				"score": 20288.0,
				"summaryTime": "2019-02-21T23:00:00+09:00"
			},
			{
				"score": 20541.0,
				"summaryTime": "2019-02-21T23:30:00+09:00"
			},
			{
				"score": 20706.0,
				"summaryTime": "2019-02-22T00:00:00+09:00"
			},
			{
				"score": 20991.0,
				"summaryTime": "2019-02-22T00:30:00+09:00"
			},
			{
				"score": 21248.0,
				"summaryTime": "2019-02-22T01:00:00+09:00"
			},
			{
				"score": 21406.0,
				"summaryTime": "2019-02-22T01:30:00+09:00"
			},
			{
				"score": 21584.0,
				"summaryTime": "2019-02-22T02:00:00+09:00"
			},
			{
				"score": 21670.0,
				"summaryTime": "2019-02-22T02:30:00+09:00"
			},
			{
				"score": 21750.0,
				"summaryTime": "2019-02-22T03:00:00+09:00"
			},
			{
				"score": 21820.0,
				"summaryTime": "2019-02-22T03:30:00+09:00"
			},
			{
				"score": 21880.0,
				"summaryTime": "2019-02-22T04:00:00+09:00"
			},
			{
				"score": 21940.0,
				"summaryTime": "2019-02-22T04:30:00+09:00"
			},
			{
				"score": 21968.0,
				"summaryTime": "2019-02-22T05:00:00+09:00"
			},
			{
				"score": 21990.0,
				"summaryTime": "2019-02-22T05:30:00+09:00"
			},
			{
				"score": 22052.0,
				"summaryTime": "2019-02-22T06:00:00+09:00"
			},
			{
				"score": 22112.0,
				"summaryTime": "2019-02-22T06:30:00+09:00"
			},
			{
				"score": 22184.0,
				"summaryTime": "2019-02-22T07:00:00+09:00"
			},
			{
				"score": 22289.0,
				"summaryTime": "2019-02-22T07:30:00+09:00"
			},
			{
				"score": 22380.0,
				"summaryTime": "2019-02-22T08:00:00+09:00"
			},
			{
				"score": 22542.0,
				"summaryTime": "2019-02-22T08:30:00+09:00"
			},
			{
				"score": 22690.0,
				"summaryTime": "2019-02-22T09:00:00+09:00"
			},
			{
				"score": 22836.0,
				"summaryTime": "2019-02-22T09:30:00+09:00"
			},
			{
				"score": 22954.0,
				"summaryTime": "2019-02-22T10:00:00+09:00"
			},
			{
				"score": 23076.0,
				"summaryTime": "2019-02-22T10:30:00+09:00"
			},
			{
				"score": 23172.0,
				"summaryTime": "2019-02-22T11:00:00+09:00"
			},
			{
				"score": 23242.0,
				"summaryTime": "2019-02-22T11:30:00+09:00"
			},
			{
				"score": 23368.0,
				"summaryTime": "2019-02-22T12:00:00+09:00"
			},
			{
				"score": 23484.0,
				"summaryTime": "2019-02-22T12:30:00+09:00"
			},
			{
				"score": 23632.0,
				"summaryTime": "2019-02-22T13:00:00+09:00"
			},
			{
				"score": 23748.0,
				"summaryTime": "2019-02-22T13:30:00+09:00"
			},
			{
				"score": 23824.0,
				"summaryTime": "2019-02-22T14:00:00+09:00"
			},
			{
				"score": 23907.0,
				"summaryTime": "2019-02-22T14:30:00+09:00"
			},
			{
				"score": 24044.0,
				"summaryTime": "2019-02-22T15:00:00+09:00"
			},
			{
				"score": 24198.0,
				"summaryTime": "2019-02-22T15:30:00+09:00"
			},
			{
				"score": 24294.0,
				"summaryTime": "2019-02-22T16:00:00+09:00"
			},
			{
				"score": 24394.0,
				"summaryTime": "2019-02-22T16:30:00+09:00"
			},
			{
				"score": 24550.0,
				"summaryTime": "2019-02-22T17:00:00+09:00"
			},
			{
				"score": 24756.0,
				"summaryTime": "2019-02-22T17:30:00+09:00"
			},
			{
				"score": 24883.0,
				"summaryTime": "2019-02-22T18:00:00+09:00"
			},
			{
				"score": 25035.0,
				"summaryTime": "2019-02-22T18:30:00+09:00"
			},
			{
				"score": 25153.0,
				"summaryTime": "2019-02-22T19:00:00+09:00"
			},
			{
				"score": 25322.0,
				"summaryTime": "2019-02-22T19:30:00+09:00"
			},
			{
				"score": 25460.0,
				"summaryTime": "2019-02-22T20:00:00+09:00"
			},
			{
				"score": 25621.0,
				"summaryTime": "2019-02-22T20:30:00+09:00"
			},
			{
				"score": 25837.0,
				"summaryTime": "2019-02-22T21:00:00+09:00"
			},
			{
				"score": 26080.0,
				"summaryTime": "2019-02-22T21:30:00+09:00"
			},
			{
				"score": 26348.0,
				"summaryTime": "2019-02-22T22:00:00+09:00"
			},
			{
				"score": 26610.0,
				"summaryTime": "2019-02-22T22:30:00+09:00"
			},
			{
				"score": 26800.0,
				"summaryTime": "2019-02-22T23:00:00+09:00"
			}
		]
	},
	{
		"rank": 10000,
		"data": [
			{
				"score": 420.0,
				"summaryTime": "2019-02-19T15:30:00+09:00"
			},
			{
				"score": 856.0,
				"summaryTime": "2019-02-19T16:00:00+09:00"
			},
			{
				"score": 1148.0,
				"summaryTime": "2019-02-19T16:30:00+09:00"
			},
			{
				"score": 1420.0,
				"summaryTime": "2019-02-19T17:00:00+09:00"
			},
			{
				"score": 1700.0,
				"summaryTime": "2019-02-19T17:30:00+09:00"
			},
			{
				"score": 1840.0,
				"summaryTime": "2019-02-19T18:00:00+09:00"
			},
			{
				"score": 1980.0,
				"summaryTime": "2019-02-19T18:30:00+09:00"
			},
			{
				"score": 2052.0,
				"summaryTime": "2019-02-19T19:00:00+09:00"
			},
			{
				"score": 2176.0,
				"summaryTime": "2019-02-19T19:30:00+09:00"
			},
			{
				"score": 2368.0,
				"summaryTime": "2019-02-19T20:00:00+09:00"
			},
			{
				"score": 2502.0,
				"summaryTime": "2019-02-19T20:30:00+09:00"
			},
			{
				"score": 2696.0,
				"summaryTime": "2019-02-19T21:00:00+09:00"
			},
			{
				"score": 2840.0,
				"summaryTime": "2019-02-19T21:30:00+09:00"
			},
			{
				"score": 3110.0,
				"summaryTime": "2019-02-19T22:00:00+09:00"
			},
			{
				"score": 3320.0,
				"summaryTime": "2019-02-19T22:30:00+09:00"
			},
			{
				"score": 3537.0,
				"summaryTime": "2019-02-19T23:00:00+09:00"
			},
			{
				"score": 3700.0,
				"summaryTime": "2019-02-19T23:30:00+09:00"
			},
			{
				"score": 3840.0,
				"summaryTime": "2019-02-20T00:00:00+09:00"
			},
			{
				"score": 4112.0,
				"summaryTime": "2019-02-20T00:30:00+09:00"
			},
			{
				"score": 4300.0,
				"summaryTime": "2019-02-20T01:00:00+09:00"
			},
			{
				"score": 4420.0,
				"summaryTime": "2019-02-20T01:30:00+09:00"
			},
			{
				"score": 4540.0,
				"summaryTime": "2019-02-20T02:00:00+09:00"
			},
			{
				"score": 4596.0,
				"summaryTime": "2019-02-20T02:30:00+09:00"
			},
			{
				"score": 4684.0,
				"summaryTime": "2019-02-20T03:00:00+09:00"
			},
			{
				"score": 4724.0,
				"summaryTime": "2019-02-20T03:30:00+09:00"
			},
			{
				"score": 4793.0,
				"summaryTime": "2019-02-20T04:00:00+09:00"
			},
			{
				"score": 4840.0,
				"summaryTime": "2019-02-20T04:30:00+09:00"
			},
			{
				"score": 4840.0,
				"summaryTime": "2019-02-20T05:00:00+09:00"
			},
			{
				"score": 4904.0,
				"summaryTime": "2019-02-20T05:30:00+09:00"
			},
			{
				"score": 4976.0,
				"summaryTime": "2019-02-20T06:00:00+09:00"
			},
			{
				"score": 5004.0,
				"summaryTime": "2019-02-20T06:30:00+09:00"
			},
			{
				"score": 5120.0,
				"summaryTime": "2019-02-20T07:00:00+09:00"
			},
			{
				"score": 5214.0,
				"summaryTime": "2019-02-20T07:30:00+09:00"
			},
			{
				"score": 5305.0,
				"summaryTime": "2019-02-20T08:00:00+09:00"
			},
			{
				"score": 5412.0,
				"summaryTime": "2019-02-20T08:30:00+09:00"
			},
			{
				"score": 5493.0,
				"summaryTime": "2019-02-20T09:00:00+09:00"
			},
			{
				"score": 5573.0,
				"summaryTime": "2019-02-20T09:30:00+09:00"
			},
			{
				"score": 5680.0,
				"summaryTime": "2019-02-20T10:00:00+09:00"
			},
			{
				"score": 5792.0,
				"summaryTime": "2019-02-20T10:30:00+09:00"
			},
			{
				"score": 5888.0,
				"summaryTime": "2019-02-20T11:00:00+09:00"
			},
			{
				"score": 6000.0,
				"summaryTime": "2019-02-20T11:30:00+09:00"
			},
			{
				"score": 6120.0,
				"summaryTime": "2019-02-20T12:00:00+09:00"
			},
			{
				"score": 6256.0,
				"summaryTime": "2019-02-20T12:30:00+09:00"
			},
			{
				"score": 6386.0,
				"summaryTime": "2019-02-20T13:00:00+09:00"
			},
			{
				"score": 6492.0,
				"summaryTime": "2019-02-20T13:30:00+09:00"
			},
			{
				"score": 6564.0,
				"summaryTime": "2019-02-20T14:00:00+09:00"
			},
			{
				"score": 6680.0,
				"summaryTime": "2019-02-20T14:30:00+09:00"
			},
			{
				"score": 6762.0,
				"summaryTime": "2019-02-20T15:00:00+09:00"
			},
			{
				"score": 6848.0,
				"summaryTime": "2019-02-20T15:30:00+09:00"
			},
			{
				"score": 6960.0,
				"summaryTime": "2019-02-20T16:00:00+09:00"
			},
			{
				"score": 7046.0,
				"summaryTime": "2019-02-20T16:30:00+09:00"
			},
			{
				"score": 7121.0,
				"summaryTime": "2019-02-20T17:00:00+09:00"
			},
			{
				"score": 7238.0,
				"summaryTime": "2019-02-20T17:30:00+09:00"
			},
			{
				"score": 7329.0,
				"summaryTime": "2019-02-20T18:00:00+09:00"
			},
			{
				"score": 7422.0,
				"summaryTime": "2019-02-20T18:30:00+09:00"
			},
			{
				"score": 7540.0,
				"summaryTime": "2019-02-20T19:00:00+09:00"
			},
			{
				"score": 7680.0,
				"summaryTime": "2019-02-20T19:30:00+09:00"
			},
			{
				"score": 7830.0,
				"summaryTime": "2019-02-20T20:00:00+09:00"
			},
			{
				"score": 8018.0,
				"summaryTime": "2019-02-20T20:30:00+09:00"
			},
			{
				"score": 8213.0,
				"summaryTime": "2019-02-20T21:00:00+09:00"
			},
			{
				"score": 8448.0,
				"summaryTime": "2019-02-20T21:30:00+09:00"
			},
			{
				"score": 8644.0,
				"summaryTime": "2019-02-20T22:00:00+09:00"
			},
			{
				"score": 8816.0,
				"summaryTime": "2019-02-20T22:30:00+09:00"
			},
			{
				"score": 8943.0,
				"summaryTime": "2019-02-20T23:00:00+09:00"
			},
			{
				"score": 9052.0,
				"summaryTime": "2019-02-20T23:30:00+09:00"
			},
			{
				"score": 9188.0,
				"summaryTime": "2019-02-21T00:00:00+09:00"
			},
			{
				"score": 9394.0,
				"summaryTime": "2019-02-21T00:30:00+09:00"
			},
			{
				"score": 9612.0,
				"summaryTime": "2019-02-21T01:00:00+09:00"
			},
			{
				"score": 9748.0,
				"summaryTime": "2019-02-21T01:30:00+09:00"
			},
			{
				"score": 9862.0,
				"summaryTime": "2019-02-21T02:00:00+09:00"
			},
			{
				"score": 9950.0,
				"summaryTime": "2019-02-21T02:30:00+09:00"
			},
			{
				"score": 10010.0,
				"summaryTime": "2019-02-21T03:00:00+09:00"
			},
			{
				"score": 10048.0,
				"summaryTime": "2019-02-21T03:30:00+09:00"
			},
			{
				"score": 10096.0,
				"summaryTime": "2019-02-21T04:00:00+09:00"
			},
			{
				"score": 10144.0,
				"summaryTime": "2019-02-21T04:30:00+09:00"
			},
			{
				"score": 10186.0,
				"summaryTime": "2019-02-21T05:00:00+09:00"
			},
			{
				"score": 10236.0,
				"summaryTime": "2019-02-21T05:30:00+09:00"
			},
			{
				"score": 10272.0,
				"summaryTime": "2019-02-21T06:00:00+09:00"
			},
			{
				"score": 10352.0,
				"summaryTime": "2019-02-21T06:30:00+09:00"
			},
			{
				"score": 10428.0,
				"summaryTime": "2019-02-21T07:00:00+09:00"
			},
			{
				"score": 10536.0,
				"summaryTime": "2019-02-21T07:30:00+09:00"
			},
			{
				"score": 10634.0,
				"summaryTime": "2019-02-21T08:00:00+09:00"
			},
			{
				"score": 10706.0,
				"summaryTime": "2019-02-21T08:30:00+09:00"
			},
			{
				"score": 10808.0,
				"summaryTime": "2019-02-21T09:00:00+09:00"
			},
			{
				"score": 10874.0,
				"summaryTime": "2019-02-21T09:30:00+09:00"
			},
			{
				"score": 10942.0,
				"summaryTime": "2019-02-21T10:00:00+09:00"
			},
			{
				"score": 11013.0,
				"summaryTime": "2019-02-21T10:30:00+09:00"
			},
			{
				"score": 11082.0,
				"summaryTime": "2019-02-21T11:00:00+09:00"
			},
			{
				"score": 11152.0,
				"summaryTime": "2019-02-21T11:30:00+09:00"
			},
			{
				"score": 11259.0,
				"summaryTime": "2019-02-21T12:00:00+09:00"
			},
			{
				"score": 11382.0,
				"summaryTime": "2019-02-21T12:30:00+09:00"
			},
			{
				"score": 11509.0,
				"summaryTime": "2019-02-21T13:00:00+09:00"
			},
			{
				"score": 11608.0,
				"summaryTime": "2019-02-21T13:30:00+09:00"
			},
			{
				"score": 11679.0,
				"summaryTime": "2019-02-21T14:00:00+09:00"
			},
			{
				"score": 11776.0,
				"summaryTime": "2019-02-21T14:30:00+09:00"
			},
			{
				"score": 11844.0,
				"summaryTime": "2019-02-21T15:00:00+09:00"
			},
			{
				"score": 11960.0,
				"summaryTime": "2019-02-21T15:30:00+09:00"
			},
			{
				"score": 12038.0,
				"summaryTime": "2019-02-21T16:00:00+09:00"
			},
			{
				"score": 12120.0,
				"summaryTime": "2019-02-21T16:30:00+09:00"
			},
			{
				"score": 12216.0,
				"summaryTime": "2019-02-21T17:00:00+09:00"
			},
			{
				"score": 12308.0,
				"summaryTime": "2019-02-21T17:30:00+09:00"
			},
			{
				"score": 12400.0,
				"summaryTime": "2019-02-21T18:00:00+09:00"
			},
			{
				"score": 12516.0,
				"summaryTime": "2019-02-21T18:30:00+09:00"
			},
			{
				"score": 12640.0,
				"summaryTime": "2019-02-21T19:00:00+09:00"
			},
			{
				"score": 12742.0,
				"summaryTime": "2019-02-21T19:30:00+09:00"
			},
			{
				"score": 12884.0,
				"summaryTime": "2019-02-21T20:00:00+09:00"
			},
			{
				"score": 13024.0,
				"summaryTime": "2019-02-21T20:30:00+09:00"
			},
			{
				"score": 13168.0,
				"summaryTime": "2019-02-21T21:00:00+09:00"
			},
			{
				"score": 13330.0,
				"summaryTime": "2019-02-21T21:30:00+09:00"
			},
			{
				"score": 13485.0,
				"summaryTime": "2019-02-21T22:00:00+09:00"
			},
			{
				"score": 13674.0,
				"summaryTime": "2019-02-21T22:30:00+09:00"
			},
			{
				"score": 13842.0,
				"summaryTime": "2019-02-21T23:00:00+09:00"
			},
			{
				"score": 14004.0,
				"summaryTime": "2019-02-21T23:30:00+09:00"
			},
			{
				"score": 14112.0,
				"summaryTime": "2019-02-22T00:00:00+09:00"
			},
			{
				"score": 14318.0,
				"summaryTime": "2019-02-22T00:30:00+09:00"
			},
			{
				"score": 14520.0,
				"summaryTime": "2019-02-22T01:00:00+09:00"
			},
			{
				"score": 14660.0,
				"summaryTime": "2019-02-22T01:30:00+09:00"
			},
			{
				"score": 14766.0,
				"summaryTime": "2019-02-22T02:00:00+09:00"
			},
			{
				"score": 14840.0,
				"summaryTime": "2019-02-22T02:30:00+09:00"
			},
			{
				"score": 14920.0,
				"summaryTime": "2019-02-22T03:00:00+09:00"
			},
			{
				"score": 14980.0,
				"summaryTime": "2019-02-22T03:30:00+09:00"
			},
			{
				"score": 15028.0,
				"summaryTime": "2019-02-22T04:00:00+09:00"
			},
			{
				"score": 15060.0,
				"summaryTime": "2019-02-22T04:30:00+09:00"
			},
			{
				"score": 15084.0,
				"summaryTime": "2019-02-22T05:00:00+09:00"
			},
			{
				"score": 15118.0,
				"summaryTime": "2019-02-22T05:30:00+09:00"
			},
			{
				"score": 15178.0,
				"summaryTime": "2019-02-22T06:00:00+09:00"
			},
			{
				"score": 15236.0,
				"summaryTime": "2019-02-22T06:30:00+09:00"
			},
			{
				"score": 15317.0,
				"summaryTime": "2019-02-22T07:00:00+09:00"
			},
			{
				"score": 15412.0,
				"summaryTime": "2019-02-22T07:30:00+09:00"
			},
			{
				"score": 15522.0,
				"summaryTime": "2019-02-22T08:00:00+09:00"
			},
			{
				"score": 15612.0,
				"summaryTime": "2019-02-22T08:30:00+09:00"
			},
			{
				"score": 15708.0,
				"summaryTime": "2019-02-22T09:00:00+09:00"
			},
			{
				"score": 15796.0,
				"summaryTime": "2019-02-22T09:30:00+09:00"
			},
			{
				"score": 15876.0,
				"summaryTime": "2019-02-22T10:00:00+09:00"
			},
			{
				"score": 15958.0,
				"summaryTime": "2019-02-22T10:30:00+09:00"
			},
			{
				"score": 16027.0,
				"summaryTime": "2019-02-22T11:00:00+09:00"
			},
			{
				"score": 16100.0,
				"summaryTime": "2019-02-22T11:30:00+09:00"
			},
			{
				"score": 16200.0,
				"summaryTime": "2019-02-22T12:00:00+09:00"
			},
			{
				"score": 16333.0,
				"summaryTime": "2019-02-22T12:30:00+09:00"
			},
			{
				"score": 16449.0,
				"summaryTime": "2019-02-22T13:00:00+09:00"
			},
			{
				"score": 16540.0,
				"summaryTime": "2019-02-22T13:30:00+09:00"
			},
			{
				"score": 16660.0,
				"summaryTime": "2019-02-22T14:00:00+09:00"
			},
			{
				"score": 16736.0,
				"summaryTime": "2019-02-22T14:30:00+09:00"
			},
			{
				"score": 16820.0,
				"summaryTime": "2019-02-22T15:00:00+09:00"
			},
			{
				"score": 16936.0,
				"summaryTime": "2019-02-22T15:30:00+09:00"
			},
			{
				"score": 17020.0,
				"summaryTime": "2019-02-22T16:00:00+09:00"
			},
			{
				"score": 17100.0,
				"summaryTime": "2019-02-22T16:30:00+09:00"
			},
			{
				"score": 17201.0,
				"summaryTime": "2019-02-22T17:00:00+09:00"
			},
			{
				"score": 17284.0,
				"summaryTime": "2019-02-22T17:30:00+09:00"
			},
			{
				"score": 17382.0,
				"summaryTime": "2019-02-22T18:00:00+09:00"
			},
			{
				"score": 17490.0,
				"summaryTime": "2019-02-22T18:30:00+09:00"
			},
			{
				"score": 17616.0,
				"summaryTime": "2019-02-22T19:00:00+09:00"
			},
			{
				"score": 17712.0,
				"summaryTime": "2019-02-22T19:30:00+09:00"
			},
			{
				"score": 17812.0,
				"summaryTime": "2019-02-22T20:00:00+09:00"
			},
			{
				"score": 17940.0,
				"summaryTime": "2019-02-22T20:30:00+09:00"
			},
			{
				"score": 18073.0,
				"summaryTime": "2019-02-22T21:00:00+09:00"
			},
			{
				"score": 18238.0,
				"summaryTime": "2019-02-22T21:30:00+09:00"
			},
			{
				"score": 18396.0,
				"summaryTime": "2019-02-22T22:00:00+09:00"
			},
			{
				"score": 18540.0,
				"summaryTime": "2019-02-22T22:30:00+09:00"
			},
			{
				"score": 18730.0,
				"summaryTime": "2019-02-22T23:00:00+09:00"
			}
		]
	},
	{
		"rank": 25000,
		"data": [
			{
				"score": 164.0,
				"summaryTime": "2019-02-19T16:00:00+09:00"
			},
			{
				"score": 280.0,
				"summaryTime": "2019-02-19T16:30:00+09:00"
			},
			{
				"score": 348.0,
				"summaryTime": "2019-02-19T17:00:00+09:00"
			},
			{
				"score": 420.0,
				"summaryTime": "2019-02-19T17:30:00+09:00"
			},
			{
				"score": 560.0,
				"summaryTime": "2019-02-19T18:00:00+09:00"
			},
			{
				"score": 560.0,
				"summaryTime": "2019-02-19T18:30:00+09:00"
			},
			{
				"score": 700.0,
				"summaryTime": "2019-02-19T19:00:00+09:00"
			},
			{
				"score": 852.0,
				"summaryTime": "2019-02-19T19:30:00+09:00"
			},
			{
				"score": 1000.0,
				"summaryTime": "2019-02-19T20:00:00+09:00"
			},
			{
				"score": 1140.0,
				"summaryTime": "2019-02-19T20:30:00+09:00"
			},
			{
				"score": 1280.0,
				"summaryTime": "2019-02-19T21:00:00+09:00"
			},
			{
				"score": 1536.0,
				"summaryTime": "2019-02-19T21:30:00+09:00"
			},
			{
				"score": 1700.0,
				"summaryTime": "2019-02-19T22:00:00+09:00"
			},
			{
				"score": 1840.0,
				"summaryTime": "2019-02-19T22:30:00+09:00"
			},
			{
				"score": 1935.0,
				"summaryTime": "2019-02-19T23:00:00+09:00"
			},
			{
				"score": 2000.0,
				"summaryTime": "2019-02-19T23:30:00+09:00"
			},
			{
				"score": 2116.0,
				"summaryTime": "2019-02-20T00:00:00+09:00"
			},
			{
				"score": 2256.0,
				"summaryTime": "2019-02-20T00:30:00+09:00"
			},
			{
				"score": 2372.0,
				"summaryTime": "2019-02-20T01:00:00+09:00"
			},
			{
				"score": 2420.0,
				"summaryTime": "2019-02-20T01:30:00+09:00"
			},
			{
				"score": 2488.0,
				"summaryTime": "2019-02-20T02:00:00+09:00"
			},
			{
				"score": 2560.0,
				"summaryTime": "2019-02-20T02:30:00+09:00"
			},
			{
				"score": 2560.0,
				"summaryTime": "2019-02-20T03:00:00+09:00"
			},
			{
				"score": 2600.0,
				"summaryTime": "2019-02-20T03:30:00+09:00"
			},
			{
				"score": 2636.0,
				"summaryTime": "2019-02-20T04:00:00+09:00"
			},
			{
				"score": 2680.0,
				"summaryTime": "2019-02-20T04:30:00+09:00"
			},
			{
				"score": 2700.0,
				"summaryTime": "2019-02-20T05:00:00+09:00"
			},
			{
				"score": 2700.0,
				"summaryTime": "2019-02-20T05:30:00+09:00"
			},
			{
				"score": 2730.0,
				"summaryTime": "2019-02-20T06:00:00+09:00"
			},
			{
				"score": 2806.0,
				"summaryTime": "2019-02-20T06:30:00+09:00"
			},
			{
				"score": 2852.0,
				"summaryTime": "2019-02-20T07:00:00+09:00"
			},
			{
				"score": 2980.0,
				"summaryTime": "2019-02-20T07:30:00+09:00"
			},
			{
				"score": 3094.0,
				"summaryTime": "2019-02-20T08:00:00+09:00"
			},
			{
				"score": 3204.0,
				"summaryTime": "2019-02-20T08:30:00+09:00"
			},
			{
				"score": 3280.0,
				"summaryTime": "2019-02-20T09:00:00+09:00"
			},
			{
				"score": 3393.0,
				"summaryTime": "2019-02-20T09:30:00+09:00"
			},
			{
				"score": 3450.0,
				"summaryTime": "2019-02-20T10:00:00+09:00"
			},
			{
				"score": 3536.0,
				"summaryTime": "2019-02-20T10:30:00+09:00"
			},
			{
				"score": 3576.0,
				"summaryTime": "2019-02-20T11:00:00+09:00"
			},
			{
				"score": 3648.0,
				"summaryTime": "2019-02-20T11:30:00+09:00"
			},
			{
				"score": 3700.0,
				"summaryTime": "2019-02-20T12:00:00+09:00"
			},
			{
				"score": 3792.0,
				"summaryTime": "2019-02-20T12:30:00+09:00"
			},
			{
				"score": 3876.0,
				"summaryTime": "2019-02-20T13:00:00+09:00"
			},
			{
				"score": 3961.0,
				"summaryTime": "2019-02-20T13:30:00+09:00"
			},
			{
				"score": 4028.0,
				"summaryTime": "2019-02-20T14:00:00+09:00"
			},
			{
				"score": 4116.0,
				"summaryTime": "2019-02-20T14:30:00+09:00"
			},
			{
				"score": 4162.0,
				"summaryTime": "2019-02-20T15:00:00+09:00"
			},
			{
				"score": 4248.0,
				"summaryTime": "2019-02-20T15:30:00+09:00"
			},
			{
				"score": 4284.0,
				"summaryTime": "2019-02-20T16:00:00+09:00"
			},
			{
				"score": 4366.0,
				"summaryTime": "2019-02-20T16:30:00+09:00"
			},
			{
				"score": 4420.0,
				"summaryTime": "2019-02-20T17:00:00+09:00"
			},
			{
				"score": 4488.0,
				"summaryTime": "2019-02-20T17:30:00+09:00"
			},
			{
				"score": 4560.0,
				"summaryTime": "2019-02-20T18:00:00+09:00"
			},
			{
				"score": 4644.0,
				"summaryTime": "2019-02-20T18:30:00+09:00"
			},
			{
				"score": 4718.0,
				"summaryTime": "2019-02-20T19:00:00+09:00"
			},
			{
				"score": 4840.0,
				"summaryTime": "2019-02-20T19:30:00+09:00"
			},
			{
				"score": 4940.0,
				"summaryTime": "2019-02-20T20:00:00+09:00"
			},
			{
				"score": 5052.0,
				"summaryTime": "2019-02-20T20:30:00+09:00"
			},
			{
				"score": 5168.0,
				"summaryTime": "2019-02-20T21:00:00+09:00"
			},
			{
				"score": 5282.0,
				"summaryTime": "2019-02-20T21:30:00+09:00"
			},
			{
				"score": 5400.0,
				"summaryTime": "2019-02-20T22:00:00+09:00"
			},
			{
				"score": 5506.0,
				"summaryTime": "2019-02-20T22:30:00+09:00"
			},
			{
				"score": 5607.0,
				"summaryTime": "2019-02-20T23:00:00+09:00"
			},
			{
				"score": 5713.0,
				"summaryTime": "2019-02-20T23:30:00+09:00"
			},
			{
				"score": 5834.0,
				"summaryTime": "2019-02-21T00:00:00+09:00"
			},
			{
				"score": 6000.0,
				"summaryTime": "2019-02-21T00:30:00+09:00"
			},
			{
				"score": 6164.0,
				"summaryTime": "2019-02-21T01:00:00+09:00"
			},
			{
				"score": 6273.0,
				"summaryTime": "2019-02-21T01:30:00+09:00"
			},
			{
				"score": 6364.0,
				"summaryTime": "2019-02-21T02:00:00+09:00"
			},
			{
				"score": 6420.0,
				"summaryTime": "2019-02-21T02:30:00+09:00"
			},
			{
				"score": 6472.0,
				"summaryTime": "2019-02-21T03:00:00+09:00"
			},
			{
				"score": 6524.0,
				"summaryTime": "2019-02-21T03:30:00+09:00"
			},
			{
				"score": 6552.0,
				"summaryTime": "2019-02-21T04:00:00+09:00"
			},
			{
				"score": 6560.0,
				"summaryTime": "2019-02-21T04:30:00+09:00"
			},
			{
				"score": 6606.0,
				"summaryTime": "2019-02-21T05:00:00+09:00"
			},
			{
				"score": 6640.0,
				"summaryTime": "2019-02-21T05:30:00+09:00"
			},
			{
				"score": 6680.0,
				"summaryTime": "2019-02-21T06:00:00+09:00"
			},
			{
				"score": 6712.0,
				"summaryTime": "2019-02-21T06:30:00+09:00"
			},
			{
				"score": 6806.0,
				"summaryTime": "2019-02-21T07:00:00+09:00"
			},
			{
				"score": 6878.0,
				"summaryTime": "2019-02-21T07:30:00+09:00"
			},
			{
				"score": 6980.0,
				"summaryTime": "2019-02-21T08:00:00+09:00"
			},
			{
				"score": 7064.0,
				"summaryTime": "2019-02-21T08:30:00+09:00"
			},
			{
				"score": 7120.0,
				"summaryTime": "2019-02-21T09:00:00+09:00"
			},
			{
				"score": 7194.0,
				"summaryTime": "2019-02-21T09:30:00+09:00"
			},
			{
				"score": 7258.0,
				"summaryTime": "2019-02-21T10:00:00+09:00"
			},
			{
				"score": 7307.0,
				"summaryTime": "2019-02-21T10:30:00+09:00"
			},
			{
				"score": 7370.0,
				"summaryTime": "2019-02-21T11:00:00+09:00"
			},
			{
				"score": 7412.0,
				"summaryTime": "2019-02-21T11:30:00+09:00"
			},
			{
				"score": 7474.0,
				"summaryTime": "2019-02-21T12:00:00+09:00"
			},
			{
				"score": 7563.0,
				"summaryTime": "2019-02-21T12:30:00+09:00"
			},
			{
				"score": 7680.0,
				"summaryTime": "2019-02-21T13:00:00+09:00"
			},
			{
				"score": 7773.0,
				"summaryTime": "2019-02-21T13:30:00+09:00"
			},
			{
				"score": 7840.0,
				"summaryTime": "2019-02-21T14:00:00+09:00"
			},
			{
				"score": 7918.0,
				"summaryTime": "2019-02-21T14:30:00+09:00"
			},
			{
				"score": 7980.0,
				"summaryTime": "2019-02-21T15:00:00+09:00"
			},
			{
				"score": 8069.0,
				"summaryTime": "2019-02-21T15:30:00+09:00"
			},
			{
				"score": 8136.0,
				"summaryTime": "2019-02-21T16:00:00+09:00"
			},
			{
				"score": 8219.0,
				"summaryTime": "2019-02-21T16:30:00+09:00"
			},
			{
				"score": 8280.0,
				"summaryTime": "2019-02-21T17:00:00+09:00"
			},
			{
				"score": 8360.0,
				"summaryTime": "2019-02-21T17:30:00+09:00"
			},
			{
				"score": 8432.0,
				"summaryTime": "2019-02-21T18:00:00+09:00"
			},
			{
				"score": 8534.0,
				"summaryTime": "2019-02-21T18:30:00+09:00"
			},
			{
				"score": 8618.0,
				"summaryTime": "2019-02-21T19:00:00+09:00"
			},
			{
				"score": 8712.0,
				"summaryTime": "2019-02-21T19:30:00+09:00"
			},
			{
				"score": 8816.0,
				"summaryTime": "2019-02-21T20:00:00+09:00"
			},
			{
				"score": 8916.0,
				"summaryTime": "2019-02-21T20:30:00+09:00"
			},
			{
				"score": 9002.0,
				"summaryTime": "2019-02-21T21:00:00+09:00"
			},
			{
				"score": 9111.0,
				"summaryTime": "2019-02-21T21:30:00+09:00"
			},
			{
				"score": 9234.0,
				"summaryTime": "2019-02-21T22:00:00+09:00"
			},
			{
				"score": 9343.0,
				"summaryTime": "2019-02-21T22:30:00+09:00"
			},
			{
				"score": 9456.0,
				"summaryTime": "2019-02-21T23:00:00+09:00"
			},
			{
				"score": 9568.0,
				"summaryTime": "2019-02-21T23:30:00+09:00"
			},
			{
				"score": 9680.0,
				"summaryTime": "2019-02-22T00:00:00+09:00"
			},
			{
				"score": 9853.0,
				"summaryTime": "2019-02-22T00:30:00+09:00"
			},
			{
				"score": 10026.0,
				"summaryTime": "2019-02-22T01:00:00+09:00"
			},
			{
				"score": 10120.0,
				"summaryTime": "2019-02-22T01:30:00+09:00"
			},
			{
				"score": 10202.0,
				"summaryTime": "2019-02-22T02:00:00+09:00"
			},
			{
				"score": 10275.0,
				"summaryTime": "2019-02-22T02:30:00+09:00"
			},
			{
				"score": 10331.0,
				"summaryTime": "2019-02-22T03:00:00+09:00"
			},
			{
				"score": 10380.0,
				"summaryTime": "2019-02-22T03:30:00+09:00"
			},
			{
				"score": 10402.0,
				"summaryTime": "2019-02-22T04:00:00+09:00"
			},
			{
				"score": 10440.0,
				"summaryTime": "2019-02-22T04:30:00+09:00"
			},
			{
				"score": 10468.0,
				"summaryTime": "2019-02-22T05:00:00+09:00"
			},
			{
				"score": 10498.0,
				"summaryTime": "2019-02-22T05:30:00+09:00"
			},
			{
				"score": 10534.0,
				"summaryTime": "2019-02-22T06:00:00+09:00"
			},
			{
				"score": 10572.0,
				"summaryTime": "2019-02-22T06:30:00+09:00"
			},
			{
				"score": 10651.0,
				"summaryTime": "2019-02-22T07:00:00+09:00"
			},
			{
				"score": 10728.0,
				"summaryTime": "2019-02-22T07:30:00+09:00"
			},
			{
				"score": 10828.0,
				"summaryTime": "2019-02-22T08:00:00+09:00"
			},
			{
				"score": 10912.0,
				"summaryTime": "2019-02-22T08:30:00+09:00"
			},
			{
				"score": 10980.0,
				"summaryTime": "2019-02-22T09:00:00+09:00"
			},
			{
				"score": 11046.0,
				"summaryTime": "2019-02-22T09:30:00+09:00"
			},
			{
				"score": 11112.0,
				"summaryTime": "2019-02-22T10:00:00+09:00"
			},
			{
				"score": 11173.0,
				"summaryTime": "2019-02-22T10:30:00+09:00"
			},
			{
				"score": 11232.0,
				"summaryTime": "2019-02-22T11:00:00+09:00"
			},
			{
				"score": 11276.0,
				"summaryTime": "2019-02-22T11:30:00+09:00"
			},
			{
				"score": 11350.0,
				"summaryTime": "2019-02-22T12:00:00+09:00"
			},
			{
				"score": 11448.0,
				"summaryTime": "2019-02-22T12:30:00+09:00"
			},
			{
				"score": 11544.0,
				"summaryTime": "2019-02-22T13:00:00+09:00"
			},
			{
				"score": 11638.0,
				"summaryTime": "2019-02-22T13:30:00+09:00"
			},
			{
				"score": 11705.0,
				"summaryTime": "2019-02-22T14:00:00+09:00"
			},
			{
				"score": 11776.0,
				"summaryTime": "2019-02-22T14:30:00+09:00"
			},
			{
				"score": 11830.0,
				"summaryTime": "2019-02-22T15:00:00+09:00"
			},
			{
				"score": 11912.0,
				"summaryTime": "2019-02-22T15:30:00+09:00"
			},
			{
				"score": 11980.0,
				"summaryTime": "2019-02-22T16:00:00+09:00"
			},
			{
				"score": 12050.0,
				"summaryTime": "2019-02-22T16:30:00+09:00"
			},
			{
				"score": 12109.0,
				"summaryTime": "2019-02-22T17:00:00+09:00"
			},
			{
				"score": 12188.0,
				"summaryTime": "2019-02-22T17:30:00+09:00"
			},
			{
				"score": 12254.0,
				"summaryTime": "2019-02-22T18:00:00+09:00"
			},
			{
				"score": 12333.0,
				"summaryTime": "2019-02-22T18:30:00+09:00"
			},
			{
				"score": 12419.0,
				"summaryTime": "2019-02-22T19:00:00+09:00"
			},
			{
				"score": 12512.0,
				"summaryTime": "2019-02-22T19:30:00+09:00"
			},
			{
				"score": 12596.0,
				"summaryTime": "2019-02-22T20:00:00+09:00"
			},
			{
				"score": 12700.0,
				"summaryTime": "2019-02-22T20:30:00+09:00"
			},
			{
				"score": 12814.0,
				"summaryTime": "2019-02-22T21:00:00+09:00"
			},
			{
				"score": 12938.0,
				"summaryTime": "2019-02-22T21:30:00+09:00"
			},
			{
				"score": 13052.0,
				"summaryTime": "2019-02-22T22:00:00+09:00"
			},
			{
				"score": 13168.0,
				"summaryTime": "2019-02-22T22:30:00+09:00"
			},
			{
				"score": 13282.0,
				"summaryTime": "2019-02-22T23:00:00+09:00"
			}
		]
	},
	{
		"rank": 50000,
		"data": [
			{
				"score": 140.0,
				"summaryTime": "2019-02-19T18:30:00+09:00"
			},
			{
				"score": 158.0,
				"summaryTime": "2019-02-19T19:00:00+09:00"
			},
			{
				"score": 215.0,
				"summaryTime": "2019-02-19T19:30:00+09:00"
			},
			{
				"score": 280.0,
				"summaryTime": "2019-02-19T20:00:00+09:00"
			},
			{
				"score": 296.0,
				"summaryTime": "2019-02-19T20:30:00+09:00"
			},
			{
				"score": 384.0,
				"summaryTime": "2019-02-19T21:00:00+09:00"
			},
			{
				"score": 420.0,
				"summaryTime": "2019-02-19T21:30:00+09:00"
			},
			{
				"score": 514.0,
				"summaryTime": "2019-02-19T22:00:00+09:00"
			},
			{
				"score": 560.0,
				"summaryTime": "2019-02-19T22:30:00+09:00"
			},
			{
				"score": 648.0,
				"summaryTime": "2019-02-19T23:00:00+09:00"
			},
			{
				"score": 716.0,
				"summaryTime": "2019-02-19T23:30:00+09:00"
			},
			{
				"score": 840.0,
				"summaryTime": "2019-02-20T00:00:00+09:00"
			},
			{
				"score": 980.0,
				"summaryTime": "2019-02-20T00:30:00+09:00"
			},
			{
				"score": 1096.0,
				"summaryTime": "2019-02-20T01:00:00+09:00"
			},
			{
				"score": 1178.0,
				"summaryTime": "2019-02-20T01:30:00+09:00"
			},
			{
				"score": 1268.0,
				"summaryTime": "2019-02-20T02:00:00+09:00"
			},
			{
				"score": 1296.0,
				"summaryTime": "2019-02-20T02:30:00+09:00"
			},
			{
				"score": 1360.0,
				"summaryTime": "2019-02-20T03:00:00+09:00"
			},
			{
				"score": 1420.0,
				"summaryTime": "2019-02-20T03:30:00+09:00"
			},
			{
				"score": 1428.0,
				"summaryTime": "2019-02-20T04:00:00+09:00"
			},
			{
				"score": 1483.0,
				"summaryTime": "2019-02-20T04:30:00+09:00"
			},
			{
				"score": 1524.0,
				"summaryTime": "2019-02-20T05:00:00+09:00"
			},
			{
				"score": 1560.0,
				"summaryTime": "2019-02-20T05:30:00+09:00"
			},
			{
				"score": 1560.0,
				"summaryTime": "2019-02-20T06:00:00+09:00"
			},
			{
				"score": 1628.0,
				"summaryTime": "2019-02-20T06:30:00+09:00"
			},
			{
				"score": 1690.0,
				"summaryTime": "2019-02-20T07:00:00+09:00"
			},
			{
				"score": 1724.0,
				"summaryTime": "2019-02-20T07:30:00+09:00"
			},
			{
				"score": 1812.0,
				"summaryTime": "2019-02-20T08:00:00+09:00"
			},
			{
				"score": 1848.0,
				"summaryTime": "2019-02-20T08:30:00+09:00"
			},
			{
				"score": 1903.0,
				"summaryTime": "2019-02-20T09:00:00+09:00"
			},
			{
				"score": 1950.0,
				"summaryTime": "2019-02-20T09:30:00+09:00"
			},
			{
				"score": 1980.0,
				"summaryTime": "2019-02-20T10:00:00+09:00"
			},
			{
				"score": 2000.0,
				"summaryTime": "2019-02-20T10:30:00+09:00"
			},
			{
				"score": 2038.0,
				"summaryTime": "2019-02-20T11:00:00+09:00"
			},
			{
				"score": 2076.0,
				"summaryTime": "2019-02-20T11:30:00+09:00"
			},
			{
				"score": 2116.0,
				"summaryTime": "2019-02-20T12:00:00+09:00"
			},
			{
				"score": 2158.0,
				"summaryTime": "2019-02-20T12:30:00+09:00"
			},
			{
				"score": 2236.0,
				"summaryTime": "2019-02-20T13:00:00+09:00"
			},
			{
				"score": 2272.0,
				"summaryTime": "2019-02-20T13:30:00+09:00"
			},
			{
				"score": 2314.0,
				"summaryTime": "2019-02-20T14:00:00+09:00"
			},
			{
				"score": 2364.0,
				"summaryTime": "2019-02-20T14:30:00+09:00"
			},
			{
				"score": 2400.0,
				"summaryTime": "2019-02-20T15:00:00+09:00"
			},
			{
				"score": 2420.0,
				"summaryTime": "2019-02-20T15:30:00+09:00"
			},
			{
				"score": 2463.0,
				"summaryTime": "2019-02-20T16:00:00+09:00"
			},
			{
				"score": 2512.0,
				"summaryTime": "2019-02-20T16:30:00+09:00"
			},
			{
				"score": 2554.0,
				"summaryTime": "2019-02-20T17:00:00+09:00"
			},
			{
				"score": 2568.0,
				"summaryTime": "2019-02-20T17:30:00+09:00"
			},
			{
				"score": 2640.0,
				"summaryTime": "2019-02-20T18:00:00+09:00"
			},
			{
				"score": 2700.0,
				"summaryTime": "2019-02-20T18:30:00+09:00"
			},
			{
				"score": 2756.0,
				"summaryTime": "2019-02-20T19:00:00+09:00"
			},
			{
				"score": 2840.0,
				"summaryTime": "2019-02-20T19:30:00+09:00"
			},
			{
				"score": 2922.0,
				"summaryTime": "2019-02-20T20:00:00+09:00"
			},
			{
				"score": 2996.0,
				"summaryTime": "2019-02-20T20:30:00+09:00"
			},
			{
				"score": 3120.0,
				"summaryTime": "2019-02-20T21:00:00+09:00"
			},
			{
				"score": 3248.0,
				"summaryTime": "2019-02-20T21:30:00+09:00"
			},
			{
				"score": 3359.0,
				"summaryTime": "2019-02-20T22:00:00+09:00"
			},
			{
				"score": 3462.0,
				"summaryTime": "2019-02-20T22:30:00+09:00"
			},
			{
				"score": 3558.0,
				"summaryTime": "2019-02-20T23:00:00+09:00"
			},
			{
				"score": 3652.0,
				"summaryTime": "2019-02-20T23:30:00+09:00"
			},
			{
				"score": 3708.0,
				"summaryTime": "2019-02-21T00:00:00+09:00"
			},
			{
				"score": 3816.0,
				"summaryTime": "2019-02-21T00:30:00+09:00"
			},
			{
				"score": 3896.0,
				"summaryTime": "2019-02-21T01:00:00+09:00"
			},
			{
				"score": 3960.0,
				"summaryTime": "2019-02-21T01:30:00+09:00"
			},
			{
				"score": 4006.0,
				"summaryTime": "2019-02-21T02:00:00+09:00"
			},
			{
				"score": 4056.0,
				"summaryTime": "2019-02-21T02:30:00+09:00"
			},
			{
				"score": 4100.0,
				"summaryTime": "2019-02-21T03:00:00+09:00"
			},
			{
				"score": 4120.0,
				"summaryTime": "2019-02-21T03:30:00+09:00"
			},
			{
				"score": 4142.0,
				"summaryTime": "2019-02-21T04:00:00+09:00"
			},
			{
				"score": 4170.0,
				"summaryTime": "2019-02-21T04:30:00+09:00"
			},
			{
				"score": 4192.0,
				"summaryTime": "2019-02-21T05:00:00+09:00"
			},
			{
				"score": 4216.0,
				"summaryTime": "2019-02-21T05:30:00+09:00"
			},
			{
				"score": 4236.0,
				"summaryTime": "2019-02-21T06:00:00+09:00"
			},
			{
				"score": 4262.0,
				"summaryTime": "2019-02-21T06:30:00+09:00"
			},
			{
				"score": 4318.0,
				"summaryTime": "2019-02-21T07:00:00+09:00"
			},
			{
				"score": 4400.0,
				"summaryTime": "2019-02-21T07:30:00+09:00"
			},
			{
				"score": 4468.0,
				"summaryTime": "2019-02-21T08:00:00+09:00"
			},
			{
				"score": 4540.0,
				"summaryTime": "2019-02-21T08:30:00+09:00"
			},
			{
				"score": 4594.0,
				"summaryTime": "2019-02-21T09:00:00+09:00"
			},
			{
				"score": 4656.0,
				"summaryTime": "2019-02-21T09:30:00+09:00"
			},
			{
				"score": 4700.0,
				"summaryTime": "2019-02-21T10:00:00+09:00"
			},
			{
				"score": 4748.0,
				"summaryTime": "2019-02-21T10:30:00+09:00"
			},
			{
				"score": 4810.0,
				"summaryTime": "2019-02-21T11:00:00+09:00"
			},
			{
				"score": 4840.0,
				"summaryTime": "2019-02-21T11:30:00+09:00"
			},
			{
				"score": 4892.0,
				"summaryTime": "2019-02-21T12:00:00+09:00"
			},
			{
				"score": 4980.0,
				"summaryTime": "2019-02-21T12:30:00+09:00"
			},
			{
				"score": 5082.0,
				"summaryTime": "2019-02-21T13:00:00+09:00"
			},
			{
				"score": 5120.0,
				"summaryTime": "2019-02-21T13:30:00+09:00"
			},
			{
				"score": 5182.0,
				"summaryTime": "2019-02-21T14:00:00+09:00"
			},
			{
				"score": 5240.0,
				"summaryTime": "2019-02-21T14:30:00+09:00"
			},
			{
				"score": 5270.0,
				"summaryTime": "2019-02-21T15:00:00+09:00"
			},
			{
				"score": 5324.0,
				"summaryTime": "2019-02-21T15:30:00+09:00"
			},
			{
				"score": 5368.0,
				"summaryTime": "2019-02-21T16:00:00+09:00"
			},
			{
				"score": 5400.0,
				"summaryTime": "2019-02-21T16:30:00+09:00"
			},
			{
				"score": 5446.0,
				"summaryTime": "2019-02-21T17:00:00+09:00"
			},
			{
				"score": 5493.0,
				"summaryTime": "2019-02-21T17:30:00+09:00"
			},
			{
				"score": 5540.0,
				"summaryTime": "2019-02-21T18:00:00+09:00"
			},
			{
				"score": 5592.0,
				"summaryTime": "2019-02-21T18:30:00+09:00"
			},
			{
				"score": 5657.0,
				"summaryTime": "2019-02-21T19:00:00+09:00"
			},
			{
				"score": 5718.0,
				"summaryTime": "2019-02-21T19:30:00+09:00"
			},
			{
				"score": 5802.0,
				"summaryTime": "2019-02-21T20:00:00+09:00"
			},
			{
				"score": 5876.0,
				"summaryTime": "2019-02-21T20:30:00+09:00"
			},
			{
				"score": 5970.0,
				"summaryTime": "2019-02-21T21:00:00+09:00"
			},
			{
				"score": 6064.0,
				"summaryTime": "2019-02-21T21:30:00+09:00"
			},
			{
				"score": 6156.0,
				"summaryTime": "2019-02-21T22:00:00+09:00"
			},
			{
				"score": 6262.0,
				"summaryTime": "2019-02-21T22:30:00+09:00"
			},
			{
				"score": 6384.0,
				"summaryTime": "2019-02-21T23:00:00+09:00"
			},
			{
				"score": 6488.0,
				"summaryTime": "2019-02-21T23:30:00+09:00"
			},
			{
				"score": 6568.0,
				"summaryTime": "2019-02-22T00:00:00+09:00"
			},
			{
				"score": 6700.0,
				"summaryTime": "2019-02-22T00:30:00+09:00"
			},
			{
				"score": 6816.0,
				"summaryTime": "2019-02-22T01:00:00+09:00"
			},
			{
				"score": 6888.0,
				"summaryTime": "2019-02-22T01:30:00+09:00"
			},
			{
				"score": 6954.0,
				"summaryTime": "2019-02-22T02:00:00+09:00"
			},
			{
				"score": 6990.0,
				"summaryTime": "2019-02-22T02:30:00+09:00"
			},
			{
				"score": 7035.0,
				"summaryTime": "2019-02-22T03:00:00+09:00"
			},
			{
				"score": 7064.0,
				"summaryTime": "2019-02-22T03:30:00+09:00"
			},
			{
				"score": 7090.0,
				"summaryTime": "2019-02-22T04:00:00+09:00"
			},
			{
				"score": 7104.0,
				"summaryTime": "2019-02-22T04:30:00+09:00"
			},
			{
				"score": 7120.0,
				"summaryTime": "2019-02-22T05:00:00+09:00"
			},
			{
				"score": 7134.0,
				"summaryTime": "2019-02-22T05:30:00+09:00"
			},
			{
				"score": 7158.0,
				"summaryTime": "2019-02-22T06:00:00+09:00"
			},
			{
				"score": 7196.0,
				"summaryTime": "2019-02-22T06:30:00+09:00"
			},
			{
				"score": 7248.0,
				"summaryTime": "2019-02-22T07:00:00+09:00"
			},
			{
				"score": 7312.0,
				"summaryTime": "2019-02-22T07:30:00+09:00"
			},
			{
				"score": 7383.0,
				"summaryTime": "2019-02-22T08:00:00+09:00"
			},
			{
				"score": 7444.0,
				"summaryTime": "2019-02-22T08:30:00+09:00"
			},
			{
				"score": 7506.0,
				"summaryTime": "2019-02-22T09:00:00+09:00"
			},
			{
				"score": 7542.0,
				"summaryTime": "2019-02-22T09:30:00+09:00"
			},
			{
				"score": 7592.0,
				"summaryTime": "2019-02-22T10:00:00+09:00"
			},
			{
				"score": 7638.0,
				"summaryTime": "2019-02-22T10:30:00+09:00"
			},
			{
				"score": 7680.0,
				"summaryTime": "2019-02-22T11:00:00+09:00"
			},
			{
				"score": 7726.0,
				"summaryTime": "2019-02-22T11:30:00+09:00"
			},
			{
				"score": 7770.0,
				"summaryTime": "2019-02-22T12:00:00+09:00"
			},
			{
				"score": 7836.0,
				"summaryTime": "2019-02-22T12:30:00+09:00"
			},
			{
				"score": 7925.0,
				"summaryTime": "2019-02-22T13:00:00+09:00"
			},
			{
				"score": 7970.0,
				"summaryTime": "2019-02-22T13:30:00+09:00"
			},
			{
				"score": 8032.0,
				"summaryTime": "2019-02-22T14:00:00+09:00"
			},
			{
				"score": 8084.0,
				"summaryTime": "2019-02-22T14:30:00+09:00"
			},
			{
				"score": 8124.0,
				"summaryTime": "2019-02-22T15:00:00+09:00"
			},
			{
				"score": 8186.0,
				"summaryTime": "2019-02-22T15:30:00+09:00"
			},
			{
				"score": 8234.0,
				"summaryTime": "2019-02-22T16:00:00+09:00"
			},
			{
				"score": 8272.0,
				"summaryTime": "2019-02-22T16:30:00+09:00"
			},
			{
				"score": 8336.0,
				"summaryTime": "2019-02-22T17:00:00+09:00"
			},
			{
				"score": 8388.0,
				"summaryTime": "2019-02-22T17:30:00+09:00"
			},
			{
				"score": 8442.0,
				"summaryTime": "2019-02-22T18:00:00+09:00"
			},
			{
				"score": 8510.0,
				"summaryTime": "2019-02-22T18:30:00+09:00"
			},
			{
				"score": 8574.0,
				"summaryTime": "2019-02-22T19:00:00+09:00"
			},
			{
				"score": 8658.0,
				"summaryTime": "2019-02-22T19:30:00+09:00"
			},
			{
				"score": 8738.0,
				"summaryTime": "2019-02-22T20:00:00+09:00"
			},
			{
				"score": 8820.0,
				"summaryTime": "2019-02-22T20:30:00+09:00"
			},
			{
				"score": 8910.0,
				"summaryTime": "2019-02-22T21:00:00+09:00"
			},
			{
				"score": 8996.0,
				"summaryTime": "2019-02-22T21:30:00+09:00"
			},
			{
				"score": 9097.0,
				"summaryTime": "2019-02-22T22:00:00+09:00"
			},
			{
				"score": 9188.0,
				"summaryTime": "2019-02-22T22:30:00+09:00"
			},
			{
				"score": 9262.0,
				"summaryTime": "2019-02-22T23:00:00+09:00"
			}
		]
	}
]